<annotation>
    <folder>TRAINING-DATA</folder>
    <filename>vlcsnap-00_04_32-00031.jpg</filename>
    <size>
        <width>1280</width>
        <height>720</height>
        <depth>3</depth>
    </size>
    <object>
        <name>DA</name>
        <bndbox>
            <xmin>859</xmin>
            <ymin>337</ymin>
            <xmax>950</xmax>
            <ymax>411</ymax>
        </bndbox>
    </object>
    <object>
        <name>DJ</name>
        <bndbox>
            <xmin>745</xmin>
            <ymin>342</ymin>
            <xmax>847</xmax>
            <ymax>418</ymax>
        </bndbox>
    </object>
    <object>
        <name>S3</name>
        <bndbox>
            <xmin>513</xmin>
            <ymin>350</ymin>
            <xmax>612</xmax>
            <ymax>427</ymax>
        </bndbox>
    </object>
    <object>
        <name>HA</name>
        <bndbox>
            <xmin>630</xmin>
            <ymin>344</ymin>
            <xmax>731</xmax>
            <ymax>424</ymax>
        </bndbox>
    </object>
    <object>
        <name>H2</name>
        <bndbox>
            <xmin>409</xmin>
            <ymin>354</ymin>
            <xmax>502</xmax>
            <ymax>425</ymax>
        </bndbox>
    </object>
</annotation>