<annotation>
    <folder>ae</folder>
    <filename>00168.jpg</filename>
    <size>
        <width>1920</width>
        <height>1080</height>
        <depth>3</depth>
    </size>
    <object>
        <name>HA</name>
        <difficult>0</difficult>
        <bndbox>
            <xmin>139</xmin>
            <ymin>348</ymin>
            <xmax>400</xmax>
            <ymax>524</ymax>
        </bndbox>
    </object>
    <object>
        <name>D9</name>
        <difficult>0</difficult>
        <bndbox>
            <xmin>431</xmin>
            <ymin>360</ymin>
            <xmax>675</xmax>
            <ymax>530</ymax>
        </bndbox>
    </object>
    <object>
        <name>HK</name>
        <difficult>0</difficult>
        <bndbox>
            <xmin>699</xmin>
            <ymin>367</ymin>
            <xmax>938</xmax>
            <ymax>538</ymax>
        </bndbox>
    </object>
    <object>
        <name>C7</name>
        <difficult>0</difficult>
        <bndbox>
            <xmin>957</xmin>
            <ymin>379</ymin>
            <xmax>1185</xmax>
            <ymax>537</ymax>
        </bndbox>
    </object>
    <object>
        <name>C9</name>
        <difficult>0</difficult>
        <bndbox>
            <xmin>1205</xmin>
            <ymin>382</ymin>
            <xmax>1418</xmax>
            <ymax>538</ymax>
        </bndbox>
    </object>
</annotation>